djangocms_text_mediumeditor/__init__.py
djangocms_text_mediumeditor/cms_plugins.py
djangocms_text_mediumeditor/forms.py
djangocms_text_mediumeditor/models.py
djangocms_text_mediumeditor/sanitizer.py
djangocms_text_mediumeditor/settings.py
djangocms_text_mediumeditor/widgets.py
djangocms_text_mediumeditor/migrations/0001_initial.py
djangocms_text_mediumeditor/migrations/__init__.py
djangocms_text_mediumeditor/static/djangocms_text_mediumeditor/css/medium-editor.min.css
djangocms_text_mediumeditor/static/djangocms_text_mediumeditor/css/themes/default.min.css
djangocms_text_mediumeditor/static/djangocms_text_mediumeditor/js/medium-editor.min.js
djangocms_text_mediumeditor/templates/cms/plugins/mediumeditor_text.html
djangocms_text_mediumeditor/templates/cms/plugins/mediumeditor_text_change_form.html
djangocms_text_mediumeditor/templates/cms/plugins/widgets/mediumeditor.html
djangocms_text_mediumeditor-0.2.0.dist-info/LICENSE
djangocms_text_mediumeditor-0.2.0.dist-info/METADATA
djangocms_text_mediumeditor-0.2.0.dist-info/WHEEL
djangocms_text_mediumeditor-0.2.0.dist-info/top_level.txt
djangocms_text_mediumeditor-0.2.0.dist-info/RECORD
