Metadata-Version: 2.1
Name: djangocms-text-mediumeditor
Version: 0.2.0
Summary: Text plugin for Django CMS which uses Medium editor
Home-page: https://github.com/RauliL/djangocms-text-mediumeditor
Author: Rauli Laine
Author-email: rauli.laine@iki.fi
License: LICENSE
Platform: OS Independent
Classifier: Development Status :: 4 - Beta
Classifier: Environment :: Web Environment
Classifier: Framework :: Django
Classifier: Framework :: Django :: 3.2
Classifier: Framework :: Django :: 3.1
Classifier: Framework :: Django :: 3.0
Classifier: Intended Audience :: Developers
Classifier: License :: OSI Approved :: MIT License
Classifier: Operating System :: OS Independent
Classifier: Programming Language :: Python
Classifier: Programming Language :: Python :: 2.7
Classifier: Programming Language :: Python :: 3.5
Classifier: Topic :: Internet :: WWW/HTTP :: Dynamic Content
Requires-Dist: bleach (>=1.4)
Requires-Dist: django-cms (>=3.3.0)
